yinglish/__init__.py
yinglish-1.0.1.dist-info/LICENSE
yinglish-1.0.1.dist-info/METADATA
yinglish-1.0.1.dist-info/WHEEL
yinglish-1.0.1.dist-info/top_level.txt
yinglish-1.0.1.dist-info/RECORD
