Metadata-Version: 2.1
Name: yinglish
Version: 1.0.1
Summary: yinglish
Home-page: https://github.com/RimoChan/yinglish
Author: RimoChan
Author-email: the@librian.net
License: UNKNOWN
Platform: UNKNOWN
Classifier: Programming Language :: Python :: 3
Classifier: Operating System :: OS Independent
